{"frames": {

"hadr_ach_icon0000":
{
	"frame": {"x":2,"y":462,"w":33,"h":33},
	"rotated": false,
	"trimmed": false,
	"spriteSourceSize": {"x":0,"y":0,"w":33,"h":33},
	"sourceSize": {"w":33,"h":33}
},
"icon_a00000":
{
	"frame": {"x":2,"y":2,"w":90,"h":90},
	"rotated": false,
	"trimmed": false,
	"spriteSourceSize": {"x":0,"y":0,"w":90,"h":90},
	"sourceSize": {"w":90,"h":90}
},
"icon_a10000":
{
	"frame": {"x":2,"y":94,"w":90,"h":90},
	"rotated": false,
	"trimmed": false,
	"spriteSourceSize": {"x":0,"y":0,"w":90,"h":90},
	"sourceSize": {"w":90,"h":90}
},
"icon_a100000":
{
	"frame": {"x":186,"y":2,"w":90,"h":90},
	"rotated": false,
	"trimmed": false,
	"spriteSourceSize": {"x":0,"y":0,"w":90,"h":90},
	"sourceSize": {"w":90,"h":90}
},
"icon_a110000":
{
	"frame": {"x":186,"y":94,"w":90,"h":90},
	"rotated": false,
	"trimmed": false,
	"spriteSourceSize": {"x":0,"y":0,"w":90,"h":90},
	"sourceSize": {"w":90,"h":90}
},
"icon_a120000":
{
	"frame": {"x":186,"y":186,"w":90,"h":90},
	"rotated": false,
	"trimmed": false,
	"spriteSourceSize": {"x":0,"y":0,"w":90,"h":90},
	"sourceSize": {"w":90,"h":90}
},
"icon_a130000":
{
	"frame": {"x":186,"y":278,"w":90,"h":90},
	"rotated": false,
	"trimmed": false,
	"spriteSourceSize": {"x":0,"y":0,"w":90,"h":90},
	"sourceSize": {"w":90,"h":90}
},
"icon_a140000":
{
	"frame": {"x":186,"y":370,"w":90,"h":90},
	"rotated": false,
	"trimmed": false,
	"spriteSourceSize": {"x":0,"y":0,"w":90,"h":90},
	"sourceSize": {"w":90,"h":90}
},
"icon_a20000":
{
	"frame": {"x":2,"y":186,"w":90,"h":90},
	"rotated": false,
	"trimmed": false,
	"spriteSourceSize": {"x":0,"y":0,"w":90,"h":90},
	"sourceSize": {"w":90,"h":90}
},
"icon_a30000":
{
	"frame": {"x":2,"y":278,"w":90,"h":90},
	"rotated": false,
	"trimmed": false,
	"spriteSourceSize": {"x":0,"y":0,"w":90,"h":90},
	"sourceSize": {"w":90,"h":90}
},
"icon_a40000":
{
	"frame": {"x":2,"y":370,"w":90,"h":90},
	"rotated": false,
	"trimmed": false,
	"spriteSourceSize": {"x":0,"y":0,"w":90,"h":90},
	"sourceSize": {"w":90,"h":90}
},
"icon_a50000":
{
	"frame": {"x":94,"y":2,"w":90,"h":90},
	"rotated": false,
	"trimmed": false,
	"spriteSourceSize": {"x":0,"y":0,"w":90,"h":90},
	"sourceSize": {"w":90,"h":90}
},
"icon_a60000":
{
	"frame": {"x":94,"y":94,"w":90,"h":90},
	"rotated": false,
	"trimmed": false,
	"spriteSourceSize": {"x":0,"y":0,"w":90,"h":90},
	"sourceSize": {"w":90,"h":90}
},
"icon_a70000":
{
	"frame": {"x":94,"y":186,"w":90,"h":90},
	"rotated": false,
	"trimmed": false,
	"spriteSourceSize": {"x":0,"y":0,"w":90,"h":90},
	"sourceSize": {"w":90,"h":90}
},
"icon_a80000":
{
	"frame": {"x":94,"y":278,"w":90,"h":90},
	"rotated": false,
	"trimmed": false,
	"spriteSourceSize": {"x":0,"y":0,"w":90,"h":90},
	"sourceSize": {"w":90,"h":90}
},
"icon_a90000":
{
	"frame": {"x":94,"y":370,"w":90,"h":90},
	"rotated": false,
	"trimmed": false,
	"spriteSourceSize": {"x":0,"y":0,"w":90,"h":90},
	"sourceSize": {"w":90,"h":90}
}},
"meta": {
	"app": "Adobe Flash Professional",
	"version": "15.0.1.179",
	"image": "ach.png",
	"format": "RGBA8888",
	"size": {"w":512,"h":512},
	"scale": "1"
}
}
